dpltest/__init__.py
dpltest/main.py
dpltest-0.0.1.dist-info/METADATA
dpltest-0.0.1.dist-info/WHEEL
dpltest-0.0.1.dist-info/top_level.txt
dpltest-0.0.1.dist-info/RECORD
