Metadata-Version: 2.1
Name: dpltest
Version: 0.0.1
Summary: testtest
Author-email: gbarctester2 <a@aol.com>
Project-URL: Homepage, https://github.com/gbarctester2/dpltest
Project-URL: Bug Tracker, https://github.com/gbarctester2/dpltest/issues
Classifier: Programming Language :: Python :: 3
Classifier: License :: OSI Approved :: MIT License
Classifier: Operating System :: OS Independent
Requires-Python: >=3.7
